{"type":"header","name":"t:sections.header-group.name","sections":{"announcement-bar":{"type":"announcement-bar","disabled":true,"custom_css":[],"settings":{"announcement_text":"","announcement_link":"shopify:\/\/pages\/email-discount","announcement_closable":false}},"advanced_content_EX8iep":{"type":"advanced-content","blocks":{"liquid_GE6iHx":{"type":"liquid","settings":{"code":"<div class=\"custom-content\">\n  <p>We donate 10% of profits  🇵🇸<\/p>\n<\/div>","width":"100%","alignment":"center"}}},"block_order":["liquid_GE6iHx"],"custom_css":["{background-color: #232629; color: white; display: flex; align-items: center; justify-content: center; height: 4vh; margin: 0;}"],"settings":{"full_width":true,"space_around":false,"lazyload_images":true}},"header":{"type":"header","blocks":{"7dcb5626-42e9-4e9d-844b-0ab2a1ac9e78":{"type":"megamenu","settings":{"menu_item":"MEN","promo_image_1":"shopify:\/\/shop_images\/AndrewTatePrayingInAMosque-ezgif.com-optimize.gif","promo_heading_1":"LEADERS","promo_text_1":"Represent your slavery to none but ﷲ ﷻ with a high-quality Thawb","promo_url_1":"shopify:\/\/collections\/all-thawbs","promo_image_2":"shopify:\/\/shop_images\/Scc583da954fc493dabfab60ed01e3732n.jpg","promo_heading_2":"BISHTA DEAL","promo_text_2":"30% off Bishtas with Purchase of a Qualifying Thawb Purchase","promo_url_2":"shopify:\/\/products\/bishta"}},"258b2d7f-9db6-4479-abfe-f2642deebf92":{"type":"megamenu","settings":{"menu_item":"WOMEN","promo_image_1":"shopify:\/\/shop_images\/17033218816586a119b36616989682.webp","promo_heading_1":"OUTFITS","promo_text_1":"Complete Outfits in One Purchase (PS: We have pockets for you)","promo_url_1":"shopify:\/\/collections\/all-abayas","promo_image_2":"shopify:\/\/shop_images\/S277b9cfc5014497fb37f70f4d9ab5c92q.webp","promo_heading_2":"KIMONOS","promo_text_2":"A modern take on the traditional women's garment","promo_url_2":"shopify:\/\/collections\/kimono-abayas"}},"86232493-d317-4a06-94f5-b5dbdd564a9f":{"type":"megamenu","settings":{"menu_item":"MORE","promo_image_1":"shopify:\/\/shop_images\/blog.gif","promo_heading_1":"PRESS","promo_text_1":"Read to learn more about Islamic knowledge","promo_url_1":"shopify:\/\/blogs\/news","promo_image_2":"shopify:\/\/shop_images\/delivery-truck.gif","promo_heading_2":"TRACK","promo_text_2":"See your order's status","promo_url_2":"shopify:\/\/pages\/track-package"}},"7da042be-beaa-4553-b083-bc44f91fd4b4":{"type":"megamenu","settings":{"menu_item":"LIFESTYLE","promo_heading_1":"MODERN ART","promo_text_1":"Upgrade your home aesthetic with Allah","promo_url_1":"shopify:\/\/collections\/paintings","promo_heading_2":"RAMADAN PREP","promo_text_2":"Celebrate the best month with the best gifts","promo_url_2":"shopify:\/\/collections\/ramadan"}}},"block_order":["7dcb5626-42e9-4e9d-844b-0ab2a1ac9e78","258b2d7f-9db6-4479-abfe-f2642deebf92","86232493-d317-4a06-94f5-b5dbdd564a9f","7da042be-beaa-4553-b083-bc44f91fd4b4"],"custom_css":[".site-nav__dropdown-link--top-level,.site-nav__dropdown-link--mega,.site-nav__link {letter-spacing: 1.5px; font-family: \"Gotham\", sans-serif; font-weight: 100; font-style: normal;}",".site-nav__link .icon.icon--wide.icon-chevron-down {display: none; \/* Hide the icon *\/}",".site-header {border-bottom: 1px solid #9f9f9f;}"],"settings":{"logo":"shopify:\/\/shop_images\/thawbslogo4_6694e3a0-66ef-4b1f-9351-a0d67e4ec126.png","logo-inverted":"shopify:\/\/shop_images\/thawbslogo4WHITE.png","desktop_logo_width":140,"mobile_logo_width":120,"main_menu_link_list":"main-menu","hover_menu":true,"main_menu_alignment":"center-split","header_sticky":true,"sticky_index":false,"sticky_collection":false}}},"order":["announcement-bar","advanced_content_EX8iep","header"]}